{
	"configurations" : 
	[
		{
			"directories" : 
			[
				{
					"build" : ".",
					"jsonFile" : "directory-.-Debug-f5ebdc15457944623624.json",
					"minimumCMakeVersion" : 
					{
						"string" : "3.26"
					},
					"projectIndex" : 0,
					"source" : ".",
					"targetIndexes" : 
					[
						0,
						1,
						2,
						3,
						4,
						5
					]
				}
			],
			"name" : "Debug",
			"projects" : 
			[
				{
					"directoryIndexes" : 
					[
						0
					],
					"name" : "Thesis",
					"targetIndexes" : 
					[
						0,
						1,
						2,
						3,
						4,
						5
					]
				}
			],
			"targets" : 
			[
				{
					"directoryIndex" : 0,
					"id" : "RISCVTargetParserTableGen::@6890427a1f51a3e7e1df",
					"jsonFile" : "target-RISCVTargetParserTableGen-Debug-3abcfee3a9fe278f4afe.json",
					"name" : "RISCVTargetParserTableGen",
					"projectIndex" : 0
				},
				{
					"directoryIndex" : 0,
					"id" : "Thesis::@6890427a1f51a3e7e1df",
					"jsonFile" : "target-Thesis-Debug-01c481002cffb288afde.json",
					"name" : "Thesis",
					"projectIndex" : 0
				},
				{
					"directoryIndex" : 0,
					"id" : "acc_gen::@6890427a1f51a3e7e1df",
					"jsonFile" : "target-acc_gen-Debug-c9b0a23ba4e269d1ab02.json",
					"name" : "acc_gen",
					"projectIndex" : 0
				},
				{
					"directoryIndex" : 0,
					"id" : "clang-tablegen-targets::@6890427a1f51a3e7e1df",
					"jsonFile" : "target-clang-tablegen-targets-Debug-7dea387b0df0500b1cb0.json",
					"name" : "clang-tablegen-targets",
					"projectIndex" : 0
				},
				{
					"directoryIndex" : 0,
					"id" : "intrinsics_gen::@6890427a1f51a3e7e1df",
					"jsonFile" : "target-intrinsics_gen-Debug-084b336681f25ad1f94d.json",
					"name" : "intrinsics_gen",
					"projectIndex" : 0
				},
				{
					"directoryIndex" : 0,
					"id" : "omp_gen::@6890427a1f51a3e7e1df",
					"jsonFile" : "target-omp_gen-Debug-03e5c61621d2dfedc2ac.json",
					"name" : "omp_gen",
					"projectIndex" : 0
				}
			]
		}
	],
	"kind" : "codemodel",
	"paths" : 
	{
		"build" : "/home/htamas/Dev/Thesis/cmake-build-debug",
		"source" : "/home/htamas/Dev/Thesis"
	},
	"version" : 
	{
		"major" : 2,
		"minor" : 5
	}
}
